timeseriesx/__init__.py
timeseriesx/base/__init__.py
timeseriesx/base/base_time_series.py
timeseriesx/base/timestamp_series.py
timeseriesx/mixins/__init__.py
timeseriesx/mixins/frequency.py
timeseriesx/mixins/time_zone.py
timeseriesx/mixins/unit.py
timeseriesx/validation/__init__.py
timeseriesx/validation/frequency.py
timeseriesx/validation/time_zone.py
timeseriesx/validation/timestamp_index.py
timeseriesx/validation/unit.py
timeseriesx-0.1.13.dist-info/AUTHORS.rst
timeseriesx-0.1.13.dist-info/LICENSE
timeseriesx-0.1.13.dist-info/METADATA
timeseriesx-0.1.13.dist-info/WHEEL
timeseriesx-0.1.13.dist-info/top_level.txt
timeseriesx-0.1.13.dist-info/RECORD
