Metadata-Version: 2.1
Name: timeseriesx
Version: 0.1.13
Summary: Manage time series data with explicit frequency and unit.
Home-page: https://github.com/carlculator/timeseriesx
Author: Alexander Schulz
Author-email: info@alexander-schulz.eu
License: MIT license
Keywords: timeseriesx
Classifier: Development Status :: 2 - Pre-Alpha
Classifier: Intended Audience :: Developers
Classifier: License :: OSI Approved :: MIT License
Classifier: Natural Language :: English
Classifier: Programming Language :: Python :: 3
Classifier: Programming Language :: Python :: 3.7
Classifier: Programming Language :: Python :: 3.8
Classifier: Programming Language :: Python :: 3.9
Requires-Python: >=3.7
License-File: LICENSE
License-File: AUTHORS.rst
Requires-Dist: pint-pandas (>=0.2)
Requires-Dist: pytz
Requires-Dist: python-dateutil
